improved_diffusion_for_SMLM/__init__.py
improved_diffusion_for_SMLM/improved_diffusion/__init__.py
improved_diffusion_for_SMLM/improved_diffusion/dist_util.py
improved_diffusion_for_SMLM/improved_diffusion/fp16_util.py
improved_diffusion_for_SMLM/improved_diffusion/gaussian_diffusion.py
improved_diffusion_for_SMLM/improved_diffusion/image_datasets.py
improved_diffusion_for_SMLM/improved_diffusion/logger.py
improved_diffusion_for_SMLM/improved_diffusion/losses.py
improved_diffusion_for_SMLM/improved_diffusion/nn.py
improved_diffusion_for_SMLM/improved_diffusion/resample.py
improved_diffusion_for_SMLM/improved_diffusion/respace.py
improved_diffusion_for_SMLM/improved_diffusion/script_util.py
improved_diffusion_for_SMLM/improved_diffusion/train_util.py
improved_diffusion_for_SMLM/improved_diffusion/unet.py
improved_diffusion_for_SMLM/scripts/__init__.py
improved_diffusion_for_SMLM/scripts/image_nll.py
improved_diffusion_for_SMLM/scripts/image_sample.py
improved_diffusion_for_SMLM/scripts/image_train.py
improved_diffusion_for_SMLM/scripts/patches.py
improved_diffusion_for_SMLM/scripts/super_res_sample.py
improved_diffusion_for_SMLM/scripts/super_res_train.py
improved_diffusion_for_SMLM-0.4.8.dist-info/LICENSE
improved_diffusion_for_SMLM-0.4.8.dist-info/METADATA
improved_diffusion_for_SMLM-0.4.8.dist-info/WHEEL
improved_diffusion_for_SMLM-0.4.8.dist-info/top_level.txt
improved_diffusion_for_SMLM-0.4.8.dist-info/RECORD
