Metadata-Version: 2.1
Name: improved-diffusion-for-SMLM
Version: 0.4.8
Download-URL: https://github.com/tavnah/improved_diffusion_for_SMLM/archive/refs/tags/v_01.tar.gz
License-File: LICENSE
Requires-Dist: blobfile >=1.0.5
Requires-Dist: torch
Requires-Dist: tqdm
